company/__init__.py
company/act.py
company/archer.py
company/foundation_one.py
company/guardant_360.py
company/oncomine.py
genomics/__init__.py
genomics/maf.py
genomics/variant.py
genomics/vcf.py
genomics/data/Ens_to_NM.tab
parser/__init__.py
parser/const.py
parser/main.py
parser/templates.py
seqslab_report_parser-0.2.4.data/data/requirements.txt
util/__init__.py
util/entities_util.py
util/misc_util.py
util/parse_gencode.py
util/pdf_util.py
seqslab_report_parser-0.2.4.dist-info/METADATA
seqslab_report_parser-0.2.4.dist-info/WHEEL
seqslab_report_parser-0.2.4.dist-info/entry_points.txt
seqslab_report_parser-0.2.4.dist-info/top_level.txt
seqslab_report_parser-0.2.4.dist-info/zip-safe
seqslab_report_parser-0.2.4.dist-info/RECORD
