Metadata-Version: 2.1
Name: seqslab-report-parser
Version: 0.2.4
Summary: Atgenomix SeqsLab Report Parser
Home-page: https://github.com/AnomeGAP/Report-Parser
Author: Sid Weng
Author-email: sid.weng@atgenomix.com
License: Apache License, Version 2.0
Project-URL: Documentation, https://docs.atgenomix.com/
Project-URL: Repository, https://github.com/atgenomix/Report-Parser.git
Platform: UNKNOWN
Classifier: Intended Audience :: Developers
Classifier: License :: OSI Approved :: MIT License
Classifier: Operating System :: OS Independent
Classifier: Programming Language :: Python
Classifier: Programming Language :: Python :: 3.8
Classifier: Programming Language :: Python :: 3.9
Requires-Python: >=3.8
Requires-Dist: pip >=22.0.4
Requires-Dist: PyMuPDF ==1.22.3
Requires-Dist: biopython ==1.81
Requires-Dist: contextlib2 ==21.6.0
Requires-Dist: mysql-connector-python ==8.1.0
Requires-Dist: numpy ==1.24.4
Requires-Dist: protobuf ==4.21.12
Requires-Dist: pyfaidx ==0.7.2.1
Requires-Dist: pyhgvs ==0.11.1
Requires-Dist: schema ==0.7.5
Requires-Dist: six ==1.16.0
Requires-Dist: importlib-resources ==6.1.0
